asyncall/__init__.py
asyncall/asyncall.py
asyncall/util.py
asyncall/adaptive/__init__.py
asyncall/adaptive/python2.py
asyncall/adaptive/python3.py
tests/adaptive/__init__.py
tests/adaptive/python2.py
tests/adaptive/python3.py
asyncall-1.0.1.dist-info/LICENSE
asyncall-1.0.1.dist-info/METADATA
asyncall-1.0.1.dist-info/WHEEL
asyncall-1.0.1.dist-info/top_level.txt
asyncall-1.0.1.dist-info/RECORD
