Metadata-Version: 2.1
Name: asyncall
Version: 1.0.1
Summary: simpler and more convenient way of asynchronous invocation
Home-page: https://github.com/tiagn/asyncall
Author: tiagn
Author-email: 347618578@qq.com
License: Apache License, Version 2.0
Platform: UNKNOWN
Classifier: Programming Language :: Python
Classifier: Programming Language :: Python :: Implementation :: CPython
Requires-Python: >=2.7
